{
 "PlatformInfo": {
  "Platform": {
   "Name": "Android",
   "BasePlatform": "Android",
   "Generator": "2024.1.0.8628"
  },
  "RootPaths": {
   "ProjectRoot": "../..",
   "SourceFilesRoot": "../../.cache",
   "SoundBanksRoot": ".",
   "ExternalSourcesInputFile": "",
   "ExternalSourcesOutputRoot": "."
  },
  "DefaultAlign": "16",
  "Settings": {
   "AutoSoundBankDefinition": "false",
   "CopyLooseStreamedMediaFiles": "true",
   "SubFoldersForGeneratedFiles": "false",
   "RemoveUnusedGeneratedFiles": "true",
   "SourceControlGeneratedFiles": "false",
   "GenerateHeaderFile": "true",
   "GenerateContentTxtFile": "true",
   "GenerateMetadataXML": "false",
   "GenerateMetadataJSON": "true",
   "GenerateAllBanksMetadata": "false",
   "GeneratePerBankMetadata": "true",
   "UseSoundBankNames": "true",
   "AllowExceedingMaxSize": "false",
   "MaxAttenuationInfo": "true",
   "EstimatedDurationInfo": "true",
   "PrintObjectGuid": "true",
   "PrintObjectPath": "true"
  },
  "FileHash": "{A9EEB0F8-7647-4917-35B6-102EEC572786}"
 }
}